LICENSE
README.md
setup.cfg
setup.py
haofs.egg-info/PKG-INFO
haofs.egg-info/SOURCES.txt
haofs.egg-info/dependency_links.txt
haofs.egg-info/requires.txt
haofs.egg-info/top_level.txt
hfs/__init__.py
hfs/models.py
hfs/utils.py